<?xml version="1.0" encoding="UTF-8"?>
<BenhNhan>
<Ma>bn1</Ma>
<Ten>đông ánh</Ten>
<Sinh>18/10/1998</Sinh>
<GioiTinh>Nam</GioiTinh>
<DienThoai>0987675332</DienThoai>
<DiaChi>hồ chí minh</DiaChi>
<DoiTuong>BHYT</DoiTuong>
<Phong>phong 1</Phong>
<TrangThai>Moi</TrangThai>
<Ngay>20/04/2026</Ngay>
</BenhNhan>

<BenhNhan>
<Ma>bn2</Ma>
<Ten>phạm văn phong</Ten>
<Sinh>18/10/1998</Sinh>
<GioiTinh>Nam</GioiTinh>
<DienThoai>0987654321</DienThoai>
<DiaChi>địa chỉ ở đâu</DiaChi>
<DoiTuong>BHYT</DoiTuong>
<Phong>phong 1</Phong>
<TrangThai>Dakham</TrangThai>
<Ngay>20/04/2026</Ngay>
</BenhNhan>

<BenhNhan>
<Ma>435</Ma>
<Ten>Phạm Văn Phong</Ten>
<Sinh>06/09/2004</Sinh>
<GioiTinh>Nam</GioiTinh>
<DienThoai>0333002954</DienThoai>
<DiaChi>Bình Dương</DiaChi>
<DoiTuong>Thu phi</DoiTuong>
<Phong>phong 1</Phong>
<TrangThai>Moi</TrangThai>
<Ngay>21/04/2026</Ngay>
</BenhNhan>

